swarms_tools/__init__.py
swarms_tools/character/__init__.py
swarms_tools/character/synthesia_tool.py
swarms_tools/communication/__init__.py
swarms_tools/communication/agent_sdk.py
swarms_tools/communication/main.py
swarms_tools/devs/__init__.py
swarms_tools/devs/code_executor.py
swarms_tools/devs/github.py
swarms_tools/finance/__init__.py
swarms_tools/finance/check_solana_address.py
swarms_tools/finance/coin_market_cap.py
swarms_tools/finance/coinbase_tool.py
swarms_tools/finance/coingecko_tool.py
swarms_tools/finance/cookies_fun.py
swarms_tools/finance/defillama_mcp_clients.py
swarms_tools/finance/defillama_mcp_tools.py
swarms_tools/finance/dex_screener.py
swarms_tools/finance/eodh_api.py
swarms_tools/finance/geckoterminal.py
swarms_tools/finance/helius_api.py
swarms_tools/finance/htx_tool.py
swarms_tools/finance/interactive_brokers.py
swarms_tools/finance/jupiter.py
swarms_tools/finance/jupiter_tools.py
swarms_tools/finance/macro_tool.py
swarms_tools/finance/okx_tool.py
swarms_tools/finance/sector_analysis.py
swarms_tools/finance/unified_solana_coin_api.py
swarms_tools/finance/uniswap_tool.py
swarms_tools/finance/yahoo_finance.py
swarms_tools/healthcare/__init__.py
swarms_tools/healthcare/epic_integration.py
swarms_tools/search/__init__.py
swarms_tools/search/bing.py
swarms_tools/search/browser_use_tool.py
swarms_tools/search/exa_search.py
swarms_tools/search/firecrawl.py
swarms_tools/search/google_search.py
swarms_tools/search/searp_search.py
swarms_tools/search/tavily_search.py
swarms_tools/search/web_scraper.py
swarms_tools/social_media/__init__.py
swarms_tools/social_media/discord.py
swarms_tools/social_media/telegram_api.py
swarms_tools/social_media/twitter_tool.py
swarms_tools/structs/__init__.py
swarms_tools/structs/tool_chainer.py
swarms_tools/utils/__init__.py
swarms_tools/utils/format_dict_into_str.py
swarms_tools/utils/formatted_string.py
swarms_tools-0.3.4.dist-info/LICENSE
swarms_tools-0.3.4.dist-info/METADATA
swarms_tools-0.3.4.dist-info/WHEEL
swarms_tools-0.3.4.dist-info/RECORD
